polybar_onlinestatus/__init__.py
polybar_onlinestatus/polybar_onlinestatus.py
polybar_onlinestatus-0.2a2.dev10.dist-info/LICENSE
polybar_onlinestatus-0.2a2.dev10.dist-info/METADATA
polybar_onlinestatus-0.2a2.dev10.dist-info/WHEEL
polybar_onlinestatus-0.2a2.dev10.dist-info/entry_points.txt
polybar_onlinestatus-0.2a2.dev10.dist-info/top_level.txt
polybar_onlinestatus-0.2a2.dev10.dist-info/RECORD
