Metadata-Version: 2.1
Name: polybar-onlinestatus
Version: 0.2a2.dev10
Summary: Polybar module to check if you are online
Home-page: https://github.com/sTiKyt/polybar-onlinestatus
Author: sTiKyt
License: UNKNOWN
Platform: UNKNOWN
Requires-Python: >=3.6.*
